trifinger_rl_datasets/__init__.py
trifinger_rl_datasets/dataset_env.py
trifinger_rl_datasets/evaluate_sim.py
trifinger_rl_datasets/evaluation.py
trifinger_rl_datasets/policy_base.py
trifinger_rl_datasets/py.typed
trifinger_rl_datasets/sampling_utils.py
trifinger_rl_datasets/sim_env.py
trifinger_rl_datasets/utils.py
trifinger_rl_datasets/data/__init__.py
trifinger_rl_datasets/data/r1_camera180.yml
trifinger_rl_datasets/data/r1_camera300.yml
trifinger_rl_datasets/data/r1_camera60.yml
trifinger_rl_datasets/data/r3_camera180.yml
trifinger_rl_datasets/data/r3_camera300.yml
trifinger_rl_datasets/data/r3_camera60.yml
trifinger_rl_datasets/data/r4_camera180.yml
trifinger_rl_datasets/data/r4_camera300.yml
trifinger_rl_datasets/data/r4_camera60.yml
trifinger_rl_datasets/data/r5_camera180.yml
trifinger_rl_datasets/data/r5_camera300.yml
trifinger_rl_datasets/data/r5_camera60.yml
trifinger_rl_datasets/data/r6_camera180.yml
trifinger_rl_datasets/data/r6_camera300.yml
trifinger_rl_datasets/data/r6_camera60.yml
trifinger_rl_datasets/data/r7_camera180.yml
trifinger_rl_datasets/data/r7_camera300.yml
trifinger_rl_datasets/data/r7_camera60.yml
trifinger_rl_datasets/data/r8_camera180.yml
trifinger_rl_datasets/data/r8_camera300.yml
trifinger_rl_datasets/data/r8_camera60.yml
trifinger_rl_datasets/data/trifingerpro_shuffle_cube_trajectory_fast.npy
trifinger_rl_datasets-1.0.3.dist-info/LICENSE
trifinger_rl_datasets-1.0.3.dist-info/METADATA
trifinger_rl_datasets-1.0.3.dist-info/WHEEL
trifinger_rl_datasets-1.0.3.dist-info/top_level.txt
trifinger_rl_datasets-1.0.3.dist-info/RECORD
