Metadata-Version: 2.1
Name: trifinger-rl-datasets
Version: 1.0.3
Summary: Gym environments which provide offline RL datasets collected on the TriFinger system.
Home-page: UNKNOWN
Author: Nico Gürtler
Author-email: nico.guertler@tuebingen.mpg.de
License: BSD 3-Clause
Keywords: offline reinforcement learning,reinforcement learning,robotics,TriFinger,Real Robot Challenge,dexterous manipulation
Platform: UNKNOWN
Requires-Dist: gymnasium
Requires-Dist: lmdb
Requires-Dist: numpy
Requires-Dist: numpy-quaternion
Requires-Dist: opencv-python
Requires-Dist: tqdm
Requires-Dist: trifinger-simulation (>=1.4.0)
Requires-Dist: zarr
